LensFlare-0.0.1.dist-info/METADATA
LensFlare-0.0.1.dist-info/RECORD
LensFlare-0.0.1.dist-info/WHEEL
LensFlare-0.0.1.dist-info/top_level.txt
lensflare/__init__.py
lensflare/__version__.py
lensflare/classification.py
lensflare/regression.py
lensflare/funcs/__init__.py
lensflare/funcs/np_funcs.py
lensflare/funcs/tf_funcs.py
lensflare/neural_network/__init__.py
lensflare/neural_network/np_models.py
lensflare/neural_network/tf_models.py
lensflare/util/__init__.py
lensflare/util/common.py
lensflare/util/dependencies.py
lensflare/util/load_simple_dataset.py
lensflare/util/minibatching.py
