Metadata-Version: 2.1
Name: LensFlare
Version: 0.0.1
Summary: A small library of hand-rolled deep learning models
Home-page: UNKNOWN
Author: Gordon MacMillan
Author-email: gmacilla@ymail.com
License: UNKNOWN
Platform: UNKNOWN
Classifier: Programming Language :: Python :: 3
Classifier: License :: OSI Approved :: MIT License
Classifier: Operating System :: OS Independent
